<?xml version="1.0" encoding="UTF-8"?>
<game GSCVersion="0.12.10" PGFVersion="0.21" title="New Blank Project"><resolutionIndependence>0</resolutionIndependence><instructions>Add game instructions here.</instructions><resolution>7</resolution><scenes><scene id="id269551" label="Initial Scene"/></scenes><longDescription>Ready to create the next hit game?  Start here.</longDescription><prototypes><actor id="id539810"/><actor id="id366259"/><actor id="id193675"/><actor id="id332109"/><actor id="id652611"/><actor id="id177770"/><actor id="id813855"/></prototypes><plugins><attributes id="playhaven"/><attributes id="qqgamecenter"><boolean id="enabled">false</boolean></attributes></plugins><networkEnabled>0</networkEnabled><attributes><text id="name">default name</text><real id="time">0</real><size id="displaySize"><real id="width">480</real><real id="height">320</real></size><text id="actorTags"></text><table name="PurchaseTable" id="id179385">PurchaseTable</table><boolean name="GameOver" id="id407842">false</boolean><integer name="Score" id="id788807">0</integer><integer name="BirdX" id="id750554">0</integer></attributes></game>
